{
  "generatedAt": "2026-06-29T01:34:09.690Z",
  "source": "https://www.eveonline.com/api/warzone/insurgency",
  "hubs": [
    {
      "key": "jita",
      "name": "Jita",
      "id": 30000142
    },
    {
      "key": "amarr",
      "name": "Amarr",
      "id": 30002187
    },
    {
      "key": "dodixie",
      "name": "Dodixie",
      "id": 30002659
    },
    {
      "key": "hek",
      "name": "Hek",
      "id": 30002053
    },
    {
      "key": "rens",
      "name": "Rens",
      "id": 30002510
    }
  ],
  "stats": {
    "systems": 22,
    "lawlessNow": 9,
    "cachedDistancesReused": 110,
    "routeCalculatedNow": 0,
    "routeErrors": 0
  },
  "systems": [
    {
      "id": 30002537,
      "name": "Amamake",
      "sec": "Low-Sec",
      "security": 0.438761248111,
      "faction": "angels",
      "campaignId": 150,
      "campaignState": "ACTIVE",
      "isLawless": true,
      "isFob": true,
      "fobOriginId": 30002537,
      "fobOriginName": "Amamake",
      "corruptionPercentage": 100,
      "corruptionState": 5,
      "corruptionDate": "2026-06-28T11:25:15.553Z",
      "suppressionPercentage": 96,
      "suppressionState": 4,
      "suppressionDate": null,
      "lawlessAgeDays": 0,
      "lawlessAgeLabel": "14h",
      "distances": {
        "jita": {
          "hubId": 30000142,
          "hubName": "Jita",
          "jumps": 15
        },
        "amarr": {
          "hubId": 30002187,
          "hubName": "Amarr",
          "jumps": 8
        },
        "dodixie": {
          "hubId": 30002659,
          "hubName": "Dodixie",
          "jumps": 7
        },
        "hek": {
          "hubId": 30002053,
          "hubName": "Hek",
          "jumps": 8
        },
        "rens": {
          "hubId": 30002510,
          "hubName": "Rens",
          "jumps": 3
        }
      },
      "routeErrors": {},
      "nearestHub": {
        "hubId": 30002510,
        "hubName": "Rens",
        "jumps": 3
      }
    },
    {
      "id": 30002066,
      "name": "Arnher",
      "sec": "Low-Sec",
      "security": 0.192099606131865,
      "faction": "angels",
      "campaignId": 150,
      "campaignState": "ACTIVE",
      "isLawless": false,
      "isFob": false,
      "fobOriginId": 30002537,
      "fobOriginName": "Amamake",
      "corruptionPercentage": 95.4,
      "corruptionState": 4,
      "corruptionDate": null,
      "suppressionPercentage": 10.35,
      "suppressionState": 1,
      "suppressionDate": null,
      "lawlessAgeDays": null,
      "lawlessAgeLabel": "-",
      "distances": {
        "jita": {
          "hubId": 30000142,
          "hubName": "Jita",
          "jumps": 12
        },
        "amarr": {
          "hubId": 30002187,
          "hubName": "Amarr",
          "jumps": 11
        },
        "dodixie": {
          "hubId": 30002659,
          "hubName": "Dodixie",
          "jumps": 10
        },
        "hek": {
          "hubId": 30002053,
          "hubName": "Hek",
          "jumps": 6
        },
        "rens": {
          "hubId": 30002510,
          "hubName": "Rens",
          "jumps": 6
        }
      },
      "routeErrors": {},
      "nearestHub": {
        "hubId": 30002053,
        "hubName": "Hek",
        "jumps": 6
      }
    },
    {
      "id": 30002542,
      "name": "Auga",
      "sec": "Low-Sec",
      "security": 0.385483820575927,
      "faction": "angels",
      "campaignId": 150,
      "campaignState": "ACTIVE",
      "isLawless": false,
      "isFob": false,
      "fobOriginId": 30002537,
      "fobOriginName": "Amamake",
      "corruptionPercentage": 79.09,
      "corruptionState": 4,
      "corruptionDate": null,
      "suppressionPercentage": 100,
      "suppressionState": 5,
      "suppressionDate": "2026-06-27T14:43:07.092Z",
      "lawlessAgeDays": null,
      "lawlessAgeLabel": "-",
      "distances": {
        "jita": {
          "hubId": 30000142,
          "hubName": "Jita",
          "jumps": 16
        },
        "amarr": {
          "hubId": 30002187,
          "hubName": "Amarr",
          "jumps": 7
        },
        "dodixie": {
          "hubId": 30002659,
          "hubName": "Dodixie",
          "jumps": 7
        },
        "hek": {
          "hubId": 30002053,
          "hubName": "Hek",
          "jumps": 8
        },
        "rens": {
          "hubId": 30002510,
          "hubName": "Rens",
          "jumps": 4
        }
      },
      "routeErrors": {},
      "nearestHub": {
        "hubId": 30002510,
        "hubName": "Rens",
        "jumps": 4
      }
    },
    {
      "id": 30002541,
      "name": "Dal",
      "sec": "Low-Sec",
      "security": 0.411359588988721,
      "faction": "angels",
      "campaignId": 150,
      "campaignState": "ACTIVE",
      "isLawless": false,
      "isFob": false,
      "fobOriginId": 30002537,
      "fobOriginName": "Amamake",
      "corruptionPercentage": 65.68,
      "corruptionState": 3,
      "corruptionDate": null,
      "suppressionPercentage": 100,
      "suppressionState": 5,
      "suppressionDate": "2026-06-26T22:42:41.300Z",
      "lawlessAgeDays": null,
      "lawlessAgeLabel": "-",
      "distances": {
        "jita": {
          "hubId": 30000142,
          "hubName": "Jita",
          "jumps": 16
        },
        "amarr": {
          "hubId": 30002187,
          "hubName": "Amarr",
          "jumps": 8
        },
        "dodixie": {
          "hubId": 30002659,
          "hubName": "Dodixie",
          "jumps": 7
        },
        "hek": {
          "hubId": 30002053,
          "hubName": "Hek",
          "jumps": 8
        },
        "rens": {
          "hubId": 30002510,
          "hubName": "Rens",
          "jumps": 4
        }
      },
      "routeErrors": {},
      "nearestHub": {
        "hubId": 30002510,
        "hubName": "Rens",
        "jumps": 4
      }
    },
    {
      "id": 30002094,
      "name": "Ebolfer",
      "sec": "Low-Sec",
      "security": 0.252911448296854,
      "faction": "angels",
      "campaignId": 150,
      "campaignState": "ACTIVE",
      "isLawless": false,
      "isFob": false,
      "fobOriginId": 30002537,
      "fobOriginName": "Amamake",
      "corruptionPercentage": 5.6,
      "corruptionState": 0,
      "corruptionDate": null,
      "suppressionPercentage": 8.4,
      "suppressionState": 0,
      "suppressionDate": null,
      "lawlessAgeDays": null,
      "lawlessAgeLabel": "-",
      "distances": {
        "jita": {
          "hubId": 30000142,
          "hubName": "Jita",
          "jumps": 15
        },
        "amarr": {
          "hubId": 30002187,
          "hubName": "Amarr",
          "jumps": 10
        },
        "dodixie": {
          "hubId": 30002659,
          "hubName": "Dodixie",
          "jumps": 8
        },
        "hek": {
          "hubId": 30002053,
          "hubName": "Hek",
          "jumps": 6
        },
        "rens": {
          "hubId": 30002510,
          "hubName": "Rens",
          "jumps": 6
        }
      },
      "routeErrors": {},
      "nearestHub": {
        "hubId": 30002053,
        "hubName": "Hek",
        "jumps": 6
      }
    },
    {
      "id": 30002099,
      "name": "Egmar",
      "sec": "Low-Sec",
      "security": 0.252871671481953,
      "faction": "angels",
      "campaignId": 150,
      "campaignState": "ACTIVE",
      "isLawless": true,
      "isFob": false,
      "fobOriginId": 30002537,
      "fobOriginName": "Amamake",
      "corruptionPercentage": 100,
      "corruptionState": 5,
      "corruptionDate": "2026-06-26T13:02:15.431Z",
      "suppressionPercentage": 13.35,
      "suppressionState": 1,
      "suppressionDate": null,
      "lawlessAgeDays": 2,
      "lawlessAgeLabel": "2d 12h",
      "distances": {
        "jita": {
          "hubId": 30000142,
          "hubName": "Jita",
          "jumps": 13
        },
        "amarr": {
          "hubId": 30002187,
          "hubName": "Amarr",
          "jumps": 10
        },
        "dodixie": {
          "hubId": 30002659,
          "hubName": "Dodixie",
          "jumps": 9
        },
        "hek": {
          "hubId": 30002053,
          "hubName": "Hek",
          "jumps": 6
        },
        "rens": {
          "hubId": 30002510,
          "hubName": "Rens",
          "jumps": 5
        }
      },
      "routeErrors": {},
      "nearestHub": {
        "hubId": 30002510,
        "hubName": "Rens",
        "jumps": 5
      }
    },
    {
      "id": 30002095,
      "name": "Eszur",
      "sec": "Low-Sec",
      "security": 0.212796293381666,
      "faction": "angels",
      "campaignId": 150,
      "campaignState": "ACTIVE",
      "isLawless": true,
      "isFob": false,
      "fobOriginId": 30002537,
      "fobOriginName": "Amamake",
      "corruptionPercentage": 100,
      "corruptionState": 5,
      "corruptionDate": "2026-06-28T21:40:42.510Z",
      "suppressionPercentage": 24.85,
      "suppressionState": 2,
      "suppressionDate": null,
      "lawlessAgeDays": 0,
      "lawlessAgeLabel": "3h",
      "distances": {
        "jita": {
          "hubId": 30000142,
          "hubName": "Jita",
          "jumps": 15
        },
        "amarr": {
          "hubId": 30002187,
          "hubName": "Amarr",
          "jumps": 9
        },
        "dodixie": {
          "hubId": 30002659,
          "hubName": "Dodixie",
          "jumps": 7
        },
        "hek": {
          "hubId": 30002053,
          "hubName": "Hek",
          "jumps": 6
        },
        "rens": {
          "hubId": 30002510,
          "hubName": "Rens",
          "jumps": 5
        }
      },
      "routeErrors": {},
      "nearestHub": {
        "hubId": 30002510,
        "hubName": "Rens",
        "jumps": 5
      }
    },
    {
      "id": 30002060,
      "name": "Evati",
      "sec": "Low-Sec",
      "security": 0.247392084054528,
      "faction": "angels",
      "campaignId": 150,
      "campaignState": "ACTIVE",
      "isLawless": false,
      "isFob": false,
      "fobOriginId": 30002537,
      "fobOriginName": "Amamake",
      "corruptionPercentage": 3.6,
      "corruptionState": 0,
      "corruptionDate": null,
      "suppressionPercentage": 2,
      "suppressionState": 0,
      "suppressionDate": null,
      "lawlessAgeDays": null,
      "lawlessAgeLabel": "-",
      "distances": {
        "jita": {
          "hubId": 30000142,
          "hubName": "Jita",
          "jumps": 11
        },
        "amarr": {
          "hubId": 30002187,
          "hubName": "Amarr",
          "jumps": 12
        },
        "dodixie": {
          "hubId": 30002659,
          "hubName": "Dodixie",
          "jumps": 9
        },
        "hek": {
          "hubId": 30002053,
          "hubName": "Hek",
          "jumps": 5
        },
        "rens": {
          "hubId": 30002510,
          "hubName": "Rens",
          "jumps": 7
        }
      },
      "routeErrors": {},
      "nearestHub": {
        "hubId": 30002053,
        "hubName": "Hek",
        "jumps": 5
      }
    },
    {
      "id": 30002517,
      "name": "Gulmorogod",
      "sec": "Low-Sec",
      "security": 0.37679403765006,
      "faction": "angels",
      "campaignId": 150,
      "campaignState": "ACTIVE",
      "isLawless": true,
      "isFob": false,
      "fobOriginId": 30002537,
      "fobOriginName": "Amamake",
      "corruptionPercentage": 100,
      "corruptionState": 5,
      "corruptionDate": "2026-06-23T14:53:20.553Z",
      "suppressionPercentage": 38,
      "suppressionState": 2,
      "suppressionDate": null,
      "lawlessAgeDays": 5,
      "lawlessAgeLabel": "5d 10h",
      "distances": {
        "jita": {
          "hubId": 30000142,
          "hubName": "Jita",
          "jumps": 14
        },
        "amarr": {
          "hubId": 30002187,
          "hubName": "Amarr",
          "jumps": 9
        },
        "dodixie": {
          "hubId": 30002659,
          "hubName": "Dodixie",
          "jumps": 8
        },
        "hek": {
          "hubId": 30002053,
          "hubName": "Hek",
          "jumps": 7
        },
        "rens": {
          "hubId": 30002510,
          "hubName": "Rens",
          "jumps": 4
        }
      },
      "routeErrors": {},
      "nearestHub": {
        "hubId": 30002510,
        "hubName": "Rens",
        "jumps": 4
      }
    },
    {
      "id": 30003068,
      "name": "Kourmonen",
      "sec": "Low-Sec",
      "security": 0.363480159478758,
      "faction": "angels",
      "campaignId": 150,
      "campaignState": "ACTIVE",
      "isLawless": false,
      "isFob": false,
      "fobOriginId": 30002537,
      "fobOriginName": "Amamake",
      "corruptionPercentage": 19.6,
      "corruptionState": 1,
      "corruptionDate": null,
      "suppressionPercentage": 37,
      "suppressionState": 2,
      "suppressionDate": null,
      "lawlessAgeDays": null,
      "lawlessAgeLabel": "-",
      "distances": {
        "jita": {
          "hubId": 30000142,
          "hubName": "Jita",
          "jumps": 17
        },
        "amarr": {
          "hubId": 30002187,
          "hubName": "Amarr",
          "jumps": 6
        },
        "dodixie": {
          "hubId": 30002659,
          "hubName": "Dodixie",
          "jumps": 8
        },
        "hek": {
          "hubId": 30002053,
          "hubName": "Hek",
          "jumps": 9
        },
        "rens": {
          "hubId": 30002510,
          "hubName": "Rens",
          "jumps": 5
        }
      },
      "routeErrors": {},
      "nearestHub": {
        "hubId": 30002510,
        "hubName": "Rens",
        "jumps": 5
      }
    },
    {
      "id": 30002539,
      "name": "Siseide",
      "sec": "Low-Sec",
      "security": 0.338351102747753,
      "faction": "angels",
      "campaignId": 150,
      "campaignState": "ACTIVE",
      "isLawless": true,
      "isFob": false,
      "fobOriginId": 30002537,
      "fobOriginName": "Amamake",
      "corruptionPercentage": 100,
      "corruptionState": 5,
      "corruptionDate": "2026-06-25T14:46:04.882Z",
      "suppressionPercentage": 27.5,
      "suppressionState": 2,
      "suppressionDate": null,
      "lawlessAgeDays": 3,
      "lawlessAgeLabel": "3d 10h",
      "distances": {
        "jita": {
          "hubId": 30000142,
          "hubName": "Jita",
          "jumps": 16
        },
        "amarr": {
          "hubId": 30002187,
          "hubName": "Amarr",
          "jumps": 8
        },
        "dodixie": {
          "hubId": 30002659,
          "hubName": "Dodixie",
          "jumps": 6
        },
        "hek": {
          "hubId": 30002053,
          "hubName": "Hek",
          "jumps": 7
        },
        "rens": {
          "hubId": 30002510,
          "hubName": "Rens",
          "jumps": 4
        }
      },
      "routeErrors": {},
      "nearestHub": {
        "hubId": 30002510,
        "hubName": "Rens",
        "jumps": 4
      }
    },
    {
      "id": 30002538,
      "name": "Vard",
      "sec": "Low-Sec",
      "security": 0.379095938438127,
      "faction": "angels",
      "campaignId": 150,
      "campaignState": "ACTIVE",
      "isLawless": false,
      "isFob": false,
      "fobOriginId": 30002537,
      "fobOriginName": "Amamake",
      "corruptionPercentage": 18.75,
      "corruptionState": 1,
      "corruptionDate": null,
      "suppressionPercentage": 26.5,
      "suppressionState": 2,
      "suppressionDate": null,
      "lawlessAgeDays": null,
      "lawlessAgeLabel": "-",
      "distances": {
        "jita": {
          "hubId": 30000142,
          "hubName": "Jita",
          "jumps": 16
        },
        "amarr": {
          "hubId": 30002187,
          "hubName": "Amarr",
          "jumps": 9
        },
        "dodixie": {
          "hubId": 30002659,
          "hubName": "Dodixie",
          "jumps": 7
        },
        "hek": {
          "hubId": 30002053,
          "hubName": "Hek",
          "jumps": 8
        },
        "rens": {
          "hubId": 30002510,
          "hubName": "Rens",
          "jumps": 4
        }
      },
      "routeErrors": {},
      "nearestHub": {
        "hubId": 30002510,
        "hubName": "Rens",
        "jumps": 4
      }
    },
    {
      "id": 30045338,
      "name": "Hikkoken",
      "sec": "Low-Sec",
      "security": 0.342755089938634,
      "faction": "guristas",
      "campaignId": 151,
      "campaignState": "ACTIVE",
      "isLawless": false,
      "isFob": false,
      "fobOriginId": 30045346,
      "fobOriginName": "Kedama",
      "corruptionPercentage": 0.6,
      "corruptionState": 0,
      "corruptionDate": null,
      "suppressionPercentage": 2.8,
      "suppressionState": 0,
      "suppressionDate": null,
      "lawlessAgeDays": null,
      "lawlessAgeLabel": "-",
      "distances": {
        "jita": {
          "hubId": 30000142,
          "hubName": "Jita",
          "jumps": 8
        },
        "amarr": {
          "hubId": 30002187,
          "hubName": "Amarr",
          "jumps": 17
        },
        "dodixie": {
          "hubId": 30002659,
          "hubName": "Dodixie",
          "jumps": 9
        },
        "hek": {
          "hubId": 30002053,
          "hubName": "Hek",
          "jumps": 13
        },
        "rens": {
          "hubId": 30002510,
          "hubName": "Rens",
          "jumps": 16
        }
      },
      "routeErrors": {},
      "nearestHub": {
        "hubId": 30000142,
        "hubName": "Jita",
        "jumps": 8
      }
    },
    {
      "id": 30045345,
      "name": "Hirri",
      "sec": "Low-Sec",
      "security": 0.335504032624278,
      "faction": "guristas",
      "campaignId": 151,
      "campaignState": "ACTIVE",
      "isLawless": false,
      "isFob": false,
      "fobOriginId": 30045346,
      "fobOriginName": "Kedama",
      "corruptionPercentage": 94,
      "corruptionState": 4,
      "corruptionDate": null,
      "suppressionPercentage": 15.95,
      "suppressionState": 1,
      "suppressionDate": null,
      "lawlessAgeDays": null,
      "lawlessAgeLabel": "-",
      "distances": {
        "jita": {
          "hubId": 30000142,
          "hubName": "Jita",
          "jumps": 6
        },
        "amarr": {
          "hubId": 30002187,
          "hubName": "Amarr",
          "jumps": 15
        },
        "dodixie": {
          "hubId": 30002659,
          "hubName": "Dodixie",
          "jumps": 9
        },
        "hek": {
          "hubId": 30002053,
          "hubName": "Hek",
          "jumps": 14
        },
        "rens": {
          "hubId": 30002510,
          "hubName": "Rens",
          "jumps": 18
        }
      },
      "routeErrors": {},
      "nearestHub": {
        "hubId": 30000142,
        "hubName": "Jita",
        "jumps": 6
      }
    },
    {
      "id": 30045346,
      "name": "Kedama",
      "sec": "Low-Sec",
      "security": 0.338464408401388,
      "faction": "guristas",
      "campaignId": 151,
      "campaignState": "ACTIVE",
      "isLawless": true,
      "isFob": true,
      "fobOriginId": 30045346,
      "fobOriginName": "Kedama",
      "corruptionPercentage": 100,
      "corruptionState": 5,
      "corruptionDate": "2026-06-27T08:15:42.981Z",
      "suppressionPercentage": 18.7,
      "suppressionState": 1,
      "suppressionDate": null,
      "lawlessAgeDays": 1,
      "lawlessAgeLabel": "1d 17h",
      "distances": {
        "jita": {
          "hubId": 30000142,
          "hubName": "Jita",
          "jumps": 5
        },
        "amarr": {
          "hubId": 30002187,
          "hubName": "Amarr",
          "jumps": 14
        },
        "dodixie": {
          "hubId": 30002659,
          "hubName": "Dodixie",
          "jumps": 9
        },
        "hek": {
          "hubId": 30002053,
          "hubName": "Hek",
          "jumps": 13
        },
        "rens": {
          "hubId": 30002510,
          "hubName": "Rens",
          "jumps": 18
        }
      },
      "routeErrors": {},
      "nearestHub": {
        "hubId": 30000142,
        "hubName": "Jita",
        "jumps": 5
      }
    },
    {
      "id": 30045352,
      "name": "Nisuwa",
      "sec": "Low-Sec",
      "security": 0.309432550412595,
      "faction": "guristas",
      "campaignId": 151,
      "campaignState": "ACTIVE",
      "isLawless": false,
      "isFob": false,
      "fobOriginId": 30045346,
      "fobOriginName": "Kedama",
      "corruptionPercentage": 26.15,
      "corruptionState": 2,
      "corruptionDate": null,
      "suppressionPercentage": 16.8,
      "suppressionState": 1,
      "suppressionDate": null,
      "lawlessAgeDays": null,
      "lawlessAgeLabel": "-",
      "distances": {
        "jita": {
          "hubId": 30000142,
          "hubName": "Jita",
          "jumps": 6
        },
        "amarr": {
          "hubId": 30002187,
          "hubName": "Amarr",
          "jumps": 15
        },
        "dodixie": {
          "hubId": 30002659,
          "hubName": "Dodixie",
          "jumps": 8
        },
        "hek": {
          "hubId": 30002053,
          "hubName": "Hek",
          "jumps": 14
        },
        "rens": {
          "hubId": 30002510,
          "hubName": "Rens",
          "jumps": 17
        }
      },
      "routeErrors": {},
      "nearestHub": {
        "hubId": 30000142,
        "hubName": "Jita",
        "jumps": 6
      }
    },
    {
      "id": 30045353,
      "name": "Pynekastoh",
      "sec": "Low-Sec",
      "security": 0.239632812646096,
      "faction": "guristas",
      "campaignId": 151,
      "campaignState": "ACTIVE",
      "isLawless": false,
      "isFob": false,
      "fobOriginId": 30045346,
      "fobOriginName": "Kedama",
      "corruptionPercentage": 4.2,
      "corruptionState": 0,
      "corruptionDate": null,
      "suppressionPercentage": 3.8,
      "suppressionState": 0,
      "suppressionDate": null,
      "lawlessAgeDays": null,
      "lawlessAgeLabel": "-",
      "distances": {
        "jita": {
          "hubId": 30000142,
          "hubName": "Jita",
          "jumps": 7
        },
        "amarr": {
          "hubId": 30002187,
          "hubName": "Amarr",
          "jumps": 16
        },
        "dodixie": {
          "hubId": 30002659,
          "hubName": "Dodixie",
          "jumps": 8
        },
        "hek": {
          "hubId": 30002053,
          "hubName": "Hek",
          "jumps": 14
        },
        "rens": {
          "hubId": 30002510,
          "hubName": "Rens",
          "jumps": 17
        }
      },
      "routeErrors": {},
      "nearestHub": {
        "hubId": 30000142,
        "hubName": "Jita",
        "jumps": 7
      }
    },
    {
      "id": 30045349,
      "name": "Rakapas",
      "sec": "Low-Sec",
      "security": 0.222780374110675,
      "faction": "guristas",
      "campaignId": 151,
      "campaignState": "ACTIVE",
      "isLawless": false,
      "isFob": false,
      "fobOriginId": 30045346,
      "fobOriginName": "Kedama",
      "corruptionPercentage": 9.4,
      "corruptionState": 0,
      "corruptionDate": null,
      "suppressionPercentage": 6,
      "suppressionState": 0,
      "suppressionDate": null,
      "lawlessAgeDays": null,
      "lawlessAgeLabel": "-",
      "distances": {
        "jita": {
          "hubId": 30000142,
          "hubName": "Jita",
          "jumps": 7
        },
        "amarr": {
          "hubId": 30002187,
          "hubName": "Amarr",
          "jumps": 16
        },
        "dodixie": {
          "hubId": 30002659,
          "hubName": "Dodixie",
          "jumps": 9
        },
        "hek": {
          "hubId": 30002053,
          "hubName": "Hek",
          "jumps": 15
        },
        "rens": {
          "hubId": 30002510,
          "hubName": "Rens",
          "jumps": 18
        }
      },
      "routeErrors": {},
      "nearestHub": {
        "hubId": 30000142,
        "hubName": "Jita",
        "jumps": 7
      }
    },
    {
      "id": 30045354,
      "name": "Reitsato",
      "sec": "Low-Sec",
      "security": 0.189510479733951,
      "faction": "guristas",
      "campaignId": 151,
      "campaignState": "ACTIVE",
      "isLawless": true,
      "isFob": false,
      "fobOriginId": 30045346,
      "fobOriginName": "Kedama",
      "corruptionPercentage": 100,
      "corruptionState": 5,
      "corruptionDate": "2026-06-28T14:46:41.626Z",
      "suppressionPercentage": 11.45,
      "suppressionState": 1,
      "suppressionDate": null,
      "lawlessAgeDays": 0,
      "lawlessAgeLabel": "10h",
      "distances": {
        "jita": {
          "hubId": 30000142,
          "hubName": "Jita",
          "jumps": 6
        },
        "amarr": {
          "hubId": 30002187,
          "hubName": "Amarr",
          "jumps": 15
        },
        "dodixie": {
          "hubId": 30002659,
          "hubName": "Dodixie",
          "jumps": 10
        },
        "hek": {
          "hubId": 30002053,
          "hubName": "Hek",
          "jumps": 14
        },
        "rens": {
          "hubId": 30002510,
          "hubName": "Rens",
          "jumps": 19
        }
      },
      "routeErrors": {},
      "nearestHub": {
        "hubId": 30000142,
        "hubName": "Jita",
        "jumps": 6
      }
    },
    {
      "id": 30002809,
      "name": "Sujarento",
      "sec": "Low-Sec",
      "security": 0.311135690039648,
      "faction": "guristas",
      "campaignId": 151,
      "campaignState": "ACTIVE",
      "isLawless": false,
      "isFob": false,
      "fobOriginId": 30045346,
      "fobOriginName": "Kedama",
      "corruptionPercentage": 35.95,
      "corruptionState": 2,
      "corruptionDate": null,
      "suppressionPercentage": 4.75,
      "suppressionState": 0,
      "suppressionDate": null,
      "lawlessAgeDays": null,
      "lawlessAgeLabel": "-",
      "distances": {
        "jita": {
          "hubId": 30000142,
          "hubName": "Jita",
          "jumps": 5
        },
        "amarr": {
          "hubId": 30002187,
          "hubName": "Amarr",
          "jumps": 14
        },
        "dodixie": {
          "hubId": 30002659,
          "hubName": "Dodixie",
          "jumps": 7
        },
        "hek": {
          "hubId": 30002053,
          "hubName": "Hek",
          "jumps": 13
        },
        "rens": {
          "hubId": 30002510,
          "hubName": "Rens",
          "jumps": 16
        }
      },
      "routeErrors": {},
      "nearestHub": {
        "hubId": 30000142,
        "hubName": "Jita",
        "jumps": 5
      }
    },
    {
      "id": 30002813,
      "name": "Tama",
      "sec": "Low-Sec",
      "security": 0.282555688333797,
      "faction": "guristas",
      "campaignId": 151,
      "campaignState": "ACTIVE",
      "isLawless": true,
      "isFob": false,
      "fobOriginId": 30045346,
      "fobOriginName": "Kedama",
      "corruptionPercentage": 100,
      "corruptionState": 5,
      "corruptionDate": "2026-06-28T04:44:26.402Z",
      "suppressionPercentage": 14.35,
      "suppressionState": 1,
      "suppressionDate": null,
      "lawlessAgeDays": 0,
      "lawlessAgeLabel": "20h",
      "distances": {
        "jita": {
          "hubId": 30000142,
          "hubName": "Jita",
          "jumps": 4
        },
        "amarr": {
          "hubId": 30002187,
          "hubName": "Amarr",
          "jumps": 13
        },
        "dodixie": {
          "hubId": 30002659,
          "hubName": "Dodixie",
          "jumps": 8
        },
        "hek": {
          "hubId": 30002053,
          "hubName": "Hek",
          "jumps": 12
        },
        "rens": {
          "hubId": 30002510,
          "hubName": "Rens",
          "jumps": 17
        }
      },
      "routeErrors": {},
      "nearestHub": {
        "hubId": 30000142,
        "hubName": "Jita",
        "jumps": 4
      }
    },
    {
      "id": 30045350,
      "name": "Teimo",
      "sec": "Low-Sec",
      "security": 0.273208222003818,
      "faction": "guristas",
      "campaignId": 151,
      "campaignState": "ACTIVE",
      "isLawless": true,
      "isFob": false,
      "fobOriginId": 30045346,
      "fobOriginName": "Kedama",
      "corruptionPercentage": 100,
      "corruptionState": 5,
      "corruptionDate": "2026-06-28T17:40:05.291Z",
      "suppressionPercentage": 13.9,
      "suppressionState": 1,
      "suppressionDate": null,
      "lawlessAgeDays": 0,
      "lawlessAgeLabel": "7h",
      "distances": {
        "jita": {
          "hubId": 30000142,
          "hubName": "Jita",
          "jumps": 6
        },
        "amarr": {
          "hubId": 30002187,
          "hubName": "Amarr",
          "jumps": 15
        },
        "dodixie": {
          "hubId": 30002659,
          "hubName": "Dodixie",
          "jumps": 10
        },
        "hek": {
          "hubId": 30002053,
          "hubName": "Hek",
          "jumps": 14
        },
        "rens": {
          "hubId": 30002510,
          "hubName": "Rens",
          "jumps": 19
        }
      },
      "routeErrors": {},
      "nearestHub": {
        "hubId": 30000142,
        "hubName": "Jita",
        "jumps": 6
      }
    }
  ]
}